pylegacy/__init__.py
pylegacy/abc.py
pylegacy/builtins.py
pylegacy/datetime.py
pylegacy/exceptions.py
pylegacy/os.py
pylegacy/shutil.py
pylegacy/tempfile.py
pylegacy/weakref.py
pylegacy-0.2.1.dist-info/LICENSE
pylegacy-0.2.1.dist-info/METADATA
pylegacy-0.2.1.dist-info/WHEEL
pylegacy-0.2.1.dist-info/top_level.txt
pylegacy-0.2.1.dist-info/RECORD
